[{"line":1,"elements":[{"start_timestamp":"2025-07-07T09:15:49.907Z","before":[{"result":{"duration":7429552000,"status":"passed"},"match":{"location":"steps.HooksClass.setup()"}}],"line":3,"name":"Successful login","description":"","id":"login-functionality;successful-login","after":[{"result":{"duration":449916300,"status":"passed"},"match":{"location":"steps.HooksClass.tearDown()"}}],"type":"scenario","keyword":"Scenario","steps":[{"result":{"duration":826784400,"status":"passed"},"line":4,"name":"User is on the login page","match":{"location":"steps.LoginSteps.user_is_on_the_login_page()"},"keyword":"Given "},{"result":{"duration":163164800,"status":"passed"},"line":5,"name":"User enters username \"standard_user\"","match":{"arguments":[{"val":"\"standard_user\"","offset":21}],"location":"steps.LoginSteps.user_enters_username(java.lang.String)"},"keyword":"When "},{"result":{"duration":126027800,"status":"passed"},"line":6,"name":"User enters password \"secret_sauce\"","match":{"arguments":[{"val":"\"secret_sauce\"","offset":21}],"location":"steps.LoginSteps.user_enters_password(java.lang.String)"},"keyword":"And "},{"result":{"duration":205394100,"status":"passed"},"line":7,"name":"User clicks the login button","match":{"location":"steps.LoginSteps.user_clicks_the_login_button()"},"keyword":"And "},{"result":{"duration":1998900,"status":"passed"},"line":8,"name":"Login should be successful","match":{"location":"steps.LoginSteps.login_should_be_successful()"},"keyword":"Then "}]},{"start_timestamp":"2025-07-07T09:15:59.151Z","before":[{"result":{"duration":5786560600,"status":"passed"},"match":{"location":"steps.HooksClass.setup()"}}],"line":19,"name":"Successful login multiple users","description":"","id":"login-functionality;successful-login-multiple-users;;2","after":[{"result":{"duration":534827600,"status":"passed"},"match":{"location":"steps.HooksClass.tearDown()"}}],"type":"scenario","keyword":"Scenario Outline","steps":[{"result":{"duration":1019616900,"status":"passed"},"line":11,"name":"User is on the login page","match":{"location":"steps.LoginSteps.user_is_on_the_login_page()"},"keyword":"Given "},{"result":{"duration":265810400,"status":"passed"},"line":12,"name":"User enters username \"standard_user\"","match":{"arguments":[{"val":"\"standard_user\"","offset":21}],"location":"steps.LoginSteps.user_enters_username(java.lang.String)"},"keyword":"When "},{"result":{"duration":137456500,"status":"passed"},"line":13,"name":"User enters password \"secret_sauce\"","match":{"arguments":[{"val":"\"secret_sauce\"","offset":21}],"location":"steps.LoginSteps.user_enters_password(java.lang.String)"},"keyword":"And "},{"result":{"duration":205610300,"status":"passed"},"line":14,"name":"User clicks the login button","match":{"location":"steps.LoginSteps.user_clicks_the_login_button()"},"keyword":"And "},{"result":{"status":"passed"},"line":15,"name":"Login should be successful","match":{"location":"steps.LoginSteps.login_should_be_successful()"},"keyword":"Then "}]},{"start_timestamp":"2025-07-07T09:16:07.115Z","before":[{"result":{"duration":5685698900,"status":"passed"},"match":{"location":"steps.HooksClass.setup()"}}],"line":20,"name":"Successful login multiple users","description":"","id":"login-functionality;successful-login-multiple-users;;3","after":[{"result":{"duration":398547400,"status":"passed"},"match":{"location":"steps.HooksClass.tearDown()"}}],"type":"scenario","keyword":"Scenario Outline","steps":[{"result":{"duration":782508300,"status":"passed"},"line":11,"name":"User is on the login page","match":{"location":"steps.LoginSteps.user_is_on_the_login_page()"},"keyword":"Given "},{"result":{"duration":154408500,"status":"passed"},"line":12,"name":"User enters username \"standard_user\"","match":{"arguments":[{"val":"\"standard_user\"","offset":21}],"location":"steps.LoginSteps.user_enters_username(java.lang.String)"},"keyword":"When "},{"result":{"duration":104850000,"status":"passed"},"line":13,"name":"User enters password \"secret_sauce\"","match":{"arguments":[{"val":"\"secret_sauce\"","offset":21}],"location":"steps.LoginSteps.user_enters_password(java.lang.String)"},"keyword":"And "},{"result":{"duration":189195400,"status":"passed"},"line":14,"name":"User clicks the login button","match":{"location":"steps.LoginSteps.user_clicks_the_login_button()"},"keyword":"And "},{"result":{"status":"passed"},"line":15,"name":"Login should be successful","match":{"location":"steps.LoginSteps.login_should_be_successful()"},"keyword":"Then "}]}],"name":"Login functionality","description":"","id":"login-functionality","keyword":"Feature","uri":"file:src/test/java/feature%20files/sample.feature","tags":[]}]